{
    "service_name": "frontend",
    "create_namespace": false,
    "vite_args": [
        "VITE_DATABASE_API_URL",
        "VITE_API_URL",
        "VITE_GOOGLE_CLIENT_ID"
    ],
    "required_vars": [
        "VITE_DATABASE_API_URL",
        "VITE_GOOGLE_CLIENT_ID"
    ],
    "csp_sources": {
        "script_src": "https://accounts.google.com https://apis.google.com https://cdn.jsdelivr.net",
        "style_src": "https://fonts.googleapis.com https://accounts.google.com https://cdn.jsdelivr.net",
        "font_src": "https://fonts.gstatic.com https://fonts.googleapis.com",
        "frame_src": "https://accounts.google.com"
    }
}
